microqiskit.py
alea/__init__.py
alea/__main__.py
alea/alea.py
alea/emotion_list.txt
alea/fortune_box/emotion/angry.txt
alea/fortune_box/emotion/boring.txt
alea/fortune_box/emotion/crazy.txt
alea/fortune_box/emotion/dissatisfaction.txt
alea/fortune_box/emotion/dog.txt
alea/fortune_box/emotion/embarrassed.txt
alea/fortune_box/emotion/excited.txt
alea/fortune_box/emotion/happy.txt
alea/fortune_box/emotion/joy.txt
alea/fortune_box/emotion/sad.txt
alea/fortune_box/emotion/sleepy.txt
alea/fortune_box/emotion/stupid.txt
alea/fortune_box/fortune/00.txt
alea/fortune_box/fortune/01.txt
alea/fortune_box/fortune/02.txt
alea/fortune_box/fortune/03.txt
alea/fortune_box/fortune/04.txt
alea/fortune_box/fortune/05.txt
alea/fortune_box/fortune/06.txt
alea/fortune_box/fortune/07.txt
alea/fortune_box/fortune/08.txt
alea/fortune_box/fortune/09.txt
alea/fortune_box/fortune/10.txt
alea/fortune_box/fortune/11.txt
alea/fortune_box/fortune/12.txt
alea/fortune_box/fortune/13.txt
alea/fortune_box/fortune/14.txt
alea/fortune_box/fortune/15.txt
alea/fortune_box/fortune/16.txt
alea/fortune_box/fortune/17.txt
alea/fortune_box/fortune/18.txt
alea/fortune_box/fortune/19.txt
alea/fortune_box/fortune/20.txt
alea/fortune_box/fortune/21.txt
alea/fortune_box/fortune/22.txt
alea/fortune_box/fortune/23.txt
alea/fortune_box/fortune/24.txt
alea/fortune_box/fortune/25.txt
alea/fortune_box/fortune/26.txt
alea/fortune_box/fortune/27.txt
alea/fortune_box/fortune/28.txt
alea/fortune_box/fortune/29.txt
alea/fortune_box/fortune/30.txt
qart/__init__.py
qart/__main__.py
qart/display.py
qcb/__init__.py
qcb/__main__.py
qcb/builder.py
qcb/parse.py
qcb_draw/__init__.py
qcb_draw/__main__.py
qcb_draw/builder.py
qcb_draw/parse.py
qsay/__init__.py
qsay/__main__.py
qsay/random_circuit.py
qunix_tools-0.1.5.2.data/scripts/alea
qunix_tools-0.1.5.2.data/scripts/qart
qunix_tools-0.1.5.2.data/scripts/qcb
qunix_tools-0.1.5.2.data/scripts/qcb_draw
qunix_tools-0.1.5.2.data/scripts/qsay
qunix_tools-0.1.5.2.dist-info/LICENSE
qunix_tools-0.1.5.2.dist-info/METADATA
qunix_tools-0.1.5.2.dist-info/NOTICE
qunix_tools-0.1.5.2.dist-info/WHEEL
qunix_tools-0.1.5.2.dist-info/top_level.txt
qunix_tools-0.1.5.2.dist-info/RECORD
