Metadata-Version: 2.1
Name: qunix-tools
Version: 0.1.5.2
Summary: Library of unix-like python programs related to Qiskit
Home-page: https://github.com/echo724/qcb
Author: QuNiX
Author-email: eunchan1001@gmail.com
License: Apache License 2.0
Platform: UNKNOWN
Classifier: Programming Language :: Python :: 3.7
Requires-Dist: qiskit (>=0.16.2)
